loading_display/README.md
loading_display/__init__.py
loading_display/loading.py
loading_display-0.2.0.dist-info/METADATA
loading_display-0.2.0.dist-info/WHEEL
loading_display-0.2.0.dist-info/licenses/LICENSE
loading_display-0.2.0.dist-info/RECORD
