Metadata-Version: 2.1
Name: loading_display
Version: 0.2.0
Summary: Simple loading bar and spinner for the terminal.
Project-URL: Homepage, https://bcde.xyz
Project-URL: Bug Tracker, https://gitlab.com/jarlv/py_packages/-/issues
Project-URL: gitlab.com, https://gitlab.com/jarlv/py_packages
Author-email: "Jarl V. Bjørgan" <jvbjorgan@gmail.com>
License-File: LICENSE
Classifier: License :: OSI Approved :: MIT License
Classifier: Operating System :: OS Independent
Classifier: Programming Language :: Python :: 3
Requires-Python: >=3.7
